[
  {
    "id": "24c4e6dc-e5df-4e9e-8060-a05db6e72e55",
    "league": "Harbinger",
    "name": "Blood Rage",
    "manual_price_override": 15.0,
    "type": 25,
    "baseType": "",
    "damage": "",
    "aps": "",
    "crit_chance": "",
    "dps": "",
    "edps": "",
    "pdps": "",
    "armour": "",
    "evasion": "",
    "shield": "",
    "sockets": "",
    "links": "",
    "mods": {},
    "quality": "15",
    "level": "",
    "ilvl": "",
    "rarity": 0,
    "corrupted": false,
    "normalize_q": null,
    "crafted": null,
    "enchanted": null,
    "last_time_saved": "2017-12-04T14:03:34.7646524-07:00",
    "estimated_value": 15.0,
    "url": null
  }
]